pyramid_mixpanel/__init__.py
pyramid_mixpanel/consumer.py
pyramid_mixpanel/py.typed
pyramid_mixpanel/query.py
pyramid_mixpanel/track.py
pyramid_mixpanel/tests/__init__.py
pyramid_mixpanel/tests/test_consumers.py
pyramid_mixpanel/tests/test_functional.py
pyramid_mixpanel/tests/test_query.py
pyramid_mixpanel/tests/test_track.py
pyramid_mixpanel-0.12.0.dist-info/LICENSE
pyramid_mixpanel-0.12.0.dist-info/METADATA
pyramid_mixpanel-0.12.0.dist-info/WHEEL
pyramid_mixpanel-0.12.0.dist-info/top_level.txt
pyramid_mixpanel-0.12.0.dist-info/RECORD
