Metadata-Version: 2.1
Name: pyramid-mixpanel
Version: 0.12.0
Summary: Opinionated Pyramid integration with Mixpanel, a user behavioural analytics platform and CRM.
Home-page: https://github.com/teamniteo/pyramid_mixpanel
Author: Niteo
Author-email: info@niteo.co
License: MIT
Keywords: pyramid mixpanel pylons web
Platform: UNKNOWN
Classifier: Development Status :: 4 - Beta
Classifier: Framework :: Pyramid
Classifier: Intended Audience :: Developers
Classifier: License :: OSI Approved :: MIT License
Classifier: Programming Language :: Python :: 3
Classifier: Programming Language :: Python :: 3.7
Classifier: Topic :: Internet :: WWW/HTTP
Classifier: Topic :: Software Development :: Libraries :: Python Modules
License-File: LICENSE
Requires-Dist: pyramid
Requires-Dist: requests
Requires-Dist: mixpanel
Requires-Dist: customerio
Provides-Extra: customerio
Requires-Dist: customerio ; extra == 'customerio'
